nexa/__init__.py
nexa/constants.py
nexa/general.py
nexa/py.typed
nexa/utils.py
nexa/cli/__init__.py
nexa/cli/entry.py
nexa/gguf/__init__.py
nexa/gguf/lib_utils.py
nexa/gguf/nexa_inference_image.py
nexa/gguf/nexa_inference_text.py
nexa/gguf/nexa_inference_vlm.py
nexa/gguf/_libs/__init__.py
nexa/gguf/_libs/cpu/__init__.py
nexa/gguf/_libs/cuda/__init__.py
nexa/gguf/_libs/macos_arm64/__init__.py
nexa/gguf/llama/__init__.py
nexa/gguf/llama/_internals_transformers.py
nexa/gguf/llama/_logger_transformers.py
nexa/gguf/llama/_utils_transformers.py
nexa/gguf/llama/llama.py
nexa/gguf/llama/llama_cache.py
nexa/gguf/llama/llama_chat_format.py
nexa/gguf/llama/llama_cpp.py
nexa/gguf/llama/llama_grammar.py
nexa/gguf/llama/llama_speculative.py
nexa/gguf/llama/llama_tokenizer.py
nexa/gguf/llama/llama_types.py
nexa/gguf/llama/llava_cpp.py
nexa/gguf/sd/__init__.py
nexa/gguf/sd/_internals_diffusion.py
nexa/gguf/sd/_logger_diffusion.py
nexa/gguf/sd/stable_diffusion.py
nexa/gguf/sd/stable_diffusion_cpp.py
nexa/gguf/server/__init__.py
nexa/gguf/server/nexa_service.py
nexa/gguf/streamlit/__init__.py
nexa/gguf/streamlit/streamlit_image_chat.py
nexa/gguf/streamlit/streamlit_text_chat.py
nexa/gguf/streamlit/streamlit_vlm.py
nexa/onnx/__init__.py
nexa/onnx/nexa_inference_image.py
nexa/onnx/nexa_inference_text.py
nexa/onnx/nexa_inference_tts.py
nexa/onnx/nexa_inference_voice.py
nexa/onnx/server/__init__.py
nexa/onnx/server/nexa_service.py
nexa/onnx/streamlit/__init__.py
nexa/onnx/streamlit/streamlit_image_chat.py
nexa/onnx/streamlit/streamlit_text_chat.py
nexa/onnx/streamlit/streamlit_tts.py
nexa/onnx/streamlit/streamlit_voice_chat.py
tests/__init__.py
tests/utils.py
tests/verify_image_generation.py
tests/verify_text_generation.py
tests/verify_vlm.py
nexaai_gpu-0.0.1.dev3.dist-info/LICENSE
nexaai_gpu-0.0.1.dev3.dist-info/METADATA
nexaai_gpu-0.0.1.dev3.dist-info/WHEEL
nexaai_gpu-0.0.1.dev3.dist-info/entry_points.txt
nexaai_gpu-0.0.1.dev3.dist-info/top_level.txt
nexaai_gpu-0.0.1.dev3.dist-info/RECORD
