Metadata-Version: 2.1
Name: nexaai-gpu
Version: 0.0.1.dev3
Summary: Nexa AI SDK
Home-page: https://github.com/NexaAI/nexa-sdk
Author: Nexa AI
Author-email: octopus@nexa4ai.com
Classifier: Programming Language :: Python :: 3 :: Only
Classifier: Programming Language :: Python :: 3.7
Classifier: Programming Language :: Python :: 3.8
Classifier: Programming Language :: Python :: 3.9
Classifier: Programming Language :: Python :: 3.10
Classifier: Programming Language :: Python :: 3.11
Classifier: Programming Language :: Python :: 3.12
Requires-Python: >=3.7
License-File: LICENSE
Requires-Dist: typing-extensions >=4.5.0
Requires-Dist: numpy >=1.20.0
Requires-Dist: diskcache >=5.6.1
Requires-Dist: jinja2 >=2.11.3
Requires-Dist: boto3 >=1.34.148
Requires-Dist: botocore >=1.34.148
Requires-Dist: fastapi
Requires-Dist: uvicorn
Requires-Dist: sse-starlette
Requires-Dist: pydantic-settings
Requires-Dist: diskcache
Requires-Dist: starlette-context
Requires-Dist: pillow
Requires-Dist: streamlit
Requires-Dist: tqdm
Requires-Dist: tabulate
Requires-Dist: pydantic
Requires-Dist: PyYAML
Requires-Dist: requests
Requires-Dist: setuptools >=42
Requires-Dist: prompt-toolkit
Provides-Extra: onnx
Requires-Dist: librosa ; extra == 'onnx'
Requires-Dist: optimum[onnxruntime] >=1.7.3 ; extra == 'onnx'
Requires-Dist: diffusers ; extra == 'onnx'
Requires-Dist: optuna ; extra == 'onnx'
Requires-Dist: soundfile ; extra == 'onnx'
Requires-Dist: streamlit-audiorec ; extra == 'onnx'
Requires-Dist: transformers ; extra == 'onnx'
Requires-Dist: ttstokenizer ; extra == 'onnx'
